{
  "version": "5",
  "dialect": "mysql",
  "id": "0eb38bab-6319-45bc-9f36-636712cd649d",
  "prevId": "11dd7033-dd6f-4d16-9a10-bafa92d61ebc",
  "tables": {
    "auditLogs": {
      "name": "auditLogs",
      "columns": {
        "id": {
          "name": "id",
          "type": "int",
          "primaryKey": false,
          "notNull": true,
          "autoincrement": true
        },
        "userId": {
          "name": "userId",
          "type": "int",
          "primaryKey": false,
          "notNull": false,
          "autoincrement": false
        },
        "action": {
          "name": "action",
          "type": "varchar(255)",
          "primaryKey": false,
          "notNull": true,
          "autoincrement": false
        },
        "entityType": {
          "name": "entityType",
          "type": "varchar(100)",
          "primaryKey": false,
          "notNull": false,
          "autoincrement": false
        },
        "entityId": {
          "name": "entityId",
          "type": "int",
          "primaryKey": false,
          "notNull": false,
          "autoincrement": false
        },
        "metadata": {
          "name": "metadata",
          "type": "text",
          "primaryKey": false,
          "notNull": false,
          "autoincrement": false
        },
        "createdAt": {
          "name": "createdAt",
          "type": "timestamp",
          "primaryKey": false,
          "notNull": true,
          "autoincrement": false,
          "default": "(now())"
        }
      },
      "indexes": {},
      "foreignKeys": {},
      "compositePrimaryKeys": {
        "auditLogs_id": {
          "name": "auditLogs_id",
          "columns": [
            "id"
          ]
        }
      },
      "uniqueConstraints": {},
      "checkConstraint": {}
    },
    "calendarDates": {
      "name": "calendarDates",
      "columns": {
        "id": {
          "name": "id",
          "type": "int",
          "primaryKey": false,
          "notNull": true,
          "autoincrement": true
        },
        "fundraiserId": {
          "name": "fundraiserId",
          "type": "int",
          "primaryKey": false,
          "notNull": true,
          "autoincrement": false
        },
        "dateValue": {
          "name": "dateValue",
          "type": "varchar(10)",
          "primaryKey": false,
          "notNull": true,
          "autoincrement": false
        },
        "amount": {
          "name": "amount",
          "type": "int",
          "primaryKey": false,
          "notNull": true,
          "autoincrement": false
        },
        "purchaserPledgeId": {
          "name": "purchaserPledgeId",
          "type": "int",
          "primaryKey": false,
          "notNull": false,
          "autoincrement": false
        },
        "purchaserName": {
          "name": "purchaserName",
          "type": "varchar(255)",
          "primaryKey": false,
          "notNull": false,
          "autoincrement": false
        },
        "purchasedAt": {
          "name": "purchasedAt",
          "type": "timestamp",
          "primaryKey": false,
          "notNull": false,
          "autoincrement": false
        },
        "createdAt": {
          "name": "createdAt",
          "type": "timestamp",
          "primaryKey": false,
          "notNull": true,
          "autoincrement": false,
          "default": "(now())"
        }
      },
      "indexes": {},
      "foreignKeys": {},
      "compositePrimaryKeys": {
        "calendarDates_id": {
          "name": "calendarDates_id",
          "columns": [
            "id"
          ]
        }
      },
      "uniqueConstraints": {},
      "checkConstraint": {}
    },
    "challengeGoals": {
      "name": "challengeGoals",
      "columns": {
        "id": {
          "name": "id",
          "type": "int",
          "primaryKey": false,
          "notNull": true,
          "autoincrement": true
        },
        "fundraiserId": {
          "name": "fundraiserId",
          "type": "int",
          "primaryKey": false,
          "notNull": true,
          "autoincrement": false
        },
        "goalAmount": {
          "name": "goalAmount",
          "type": "int",
          "primaryKey": false,
          "notNull": true,
          "autoincrement": false
        },
        "challengeDescription": {
          "name": "challengeDescription",
          "type": "text",
          "primaryKey": false,
          "notNull": true,
          "autoincrement": false
        },
        "completedDescription": {
          "name": "completedDescription",
          "type": "text",
          "primaryKey": false,
          "notNull": false,
          "autoincrement": false
        },
        "isCompleted": {
          "name": "isCompleted",
          "type": "int",
          "primaryKey": false,
          "notNull": true,
          "autoincrement": false,
          "default": 0
        },
        "completedAt": {
          "name": "completedAt",
          "type": "timestamp",
          "primaryKey": false,
          "notNull": false,
          "autoincrement": false
        },
        "createdAt": {
          "name": "createdAt",
          "type": "timestamp",
          "primaryKey": false,
          "notNull": true,
          "autoincrement": false,
          "default": "(now())"
        }
      },
      "indexes": {},
      "foreignKeys": {},
      "compositePrimaryKeys": {
        "challengeGoals_id": {
          "name": "challengeGoals_id",
          "columns": [
            "id"
          ]
        }
      },
      "uniqueConstraints": {},
      "checkConstraint": {}
    },
    "charges": {
      "name": "charges",
      "columns": {
        "id": {
          "name": "id",
          "type": "int",
          "primaryKey": false,
          "notNull": true,
          "autoincrement": true
        },
        "pledgeId": {
          "name": "pledgeId",
          "type": "int",
          "primaryKey": false,
          "notNull": true,
          "autoincrement": false
        },
        "fundraiserId": {
          "name": "fundraiserId",
          "type": "int",
          "primaryKey": false,
          "notNull": true,
          "autoincrement": false
        },
        "grossAmount": {
          "name": "grossAmount",
          "type": "int",
          "primaryKey": false,
          "notNull": true,
          "autoincrement": false
        },
        "platformFee": {
          "name": "platformFee",
          "type": "int",
          "primaryKey": false,
          "notNull": true,
          "autoincrement": false
        },
        "donorTip": {
          "name": "donorTip",
          "type": "int",
          "primaryKey": false,
          "notNull": true,
          "autoincrement": false,
          "default": 0
        },
        "netAmount": {
          "name": "netAmount",
          "type": "int",
          "primaryKey": false,
          "notNull": true,
          "autoincrement": false
        },
        "stripePaymentIntentId": {
          "name": "stripePaymentIntentId",
          "type": "varchar(255)",
          "primaryKey": false,
          "notNull": false,
          "autoincrement": false
        },
        "status": {
          "name": "status",
          "type": "enum('succeeded','failed','refunded')",
          "primaryKey": false,
          "notNull": true,
          "autoincrement": false
        },
        "failureCode": {
          "name": "failureCode",
          "type": "varchar(255)",
          "primaryKey": false,
          "notNull": false,
          "autoincrement": false
        },
        "failureMessage": {
          "name": "failureMessage",
          "type": "text",
          "primaryKey": false,
          "notNull": false,
          "autoincrement": false
        },
        "refundAmount": {
          "name": "refundAmount",
          "type": "int",
          "primaryKey": false,
          "notNull": false,
          "autoincrement": false
        },
        "refundReason": {
          "name": "refundReason",
          "type": "text",
          "primaryKey": false,
          "notNull": false,
          "autoincrement": false
        },
        "succeededAt": {
          "name": "succeededAt",
          "type": "timestamp",
          "primaryKey": false,
          "notNull": false,
          "autoincrement": false
        },
        "failedAt": {
          "name": "failedAt",
          "type": "timestamp",
          "primaryKey": false,
          "notNull": false,
          "autoincrement": false
        },
        "refundedAt": {
          "name": "refundedAt",
          "type": "timestamp",
          "primaryKey": false,
          "notNull": false,
          "autoincrement": false
        },
        "createdAt": {
          "name": "createdAt",
          "type": "timestamp",
          "primaryKey": false,
          "notNull": true,
          "autoincrement": false,
          "default": "(now())"
        },
        "updatedAt": {
          "name": "updatedAt",
          "type": "timestamp",
          "primaryKey": false,
          "notNull": true,
          "autoincrement": false,
          "onUpdate": true,
          "default": "(now())"
        }
      },
      "indexes": {},
      "foreignKeys": {},
      "compositePrimaryKeys": {
        "charges_id": {
          "name": "charges_id",
          "columns": [
            "id"
          ]
        }
      },
      "uniqueConstraints": {},
      "checkConstraint": {}
    },
    "donationMatching": {
      "name": "donationMatching",
      "columns": {
        "id": {
          "name": "id",
          "type": "int",
          "primaryKey": false,
          "notNull": true,
          "autoincrement": true
        },
        "fundraiserId": {
          "name": "fundraiserId",
          "type": "int",
          "primaryKey": false,
          "notNull": true,
          "autoincrement": false
        },
        "sponsorName": {
          "name": "sponsorName",
          "type": "varchar(255)",
          "primaryKey": false,
          "notNull": true,
          "autoincrement": false
        },
        "sponsorLogoUrl": {
          "name": "sponsorLogoUrl",
          "type": "varchar(500)",
          "primaryKey": false,
          "notNull": false,
          "autoincrement": false
        },
        "matchAmount": {
          "name": "matchAmount",
          "type": "int",
          "primaryKey": false,
          "notNull": true,
          "autoincrement": false
        },
        "matchRatio": {
          "name": "matchRatio",
          "type": "int",
          "primaryKey": false,
          "notNull": true,
          "autoincrement": false,
          "default": 100
        },
        "currentMatched": {
          "name": "currentMatched",
          "type": "int",
          "primaryKey": false,
          "notNull": true,
          "autoincrement": false,
          "default": 0
        },
        "expiresAt": {
          "name": "expiresAt",
          "type": "timestamp",
          "primaryKey": false,
          "notNull": false,
          "autoincrement": false
        },
        "createdAt": {
          "name": "createdAt",
          "type": "timestamp",
          "primaryKey": false,
          "notNull": true,
          "autoincrement": false,
          "default": "(now())"
        }
      },
      "indexes": {},
      "foreignKeys": {},
      "compositePrimaryKeys": {
        "donationMatching_id": {
          "name": "donationMatching_id",
          "columns": [
            "id"
          ]
        }
      },
      "uniqueConstraints": {},
      "checkConstraint": {}
    },
    "fundraisers": {
      "name": "fundraisers",
      "columns": {
        "id": {
          "name": "id",
          "type": "int",
          "primaryKey": false,
          "notNull": true,
          "autoincrement": true
        },
        "teamId": {
          "name": "teamId",
          "type": "int",
          "primaryKey": false,
          "notNull": true,
          "autoincrement": false
        },
        "title": {
          "name": "title",
          "type": "varchar(255)",
          "primaryKey": false,
          "notNull": true,
          "autoincrement": false
        },
        "description": {
          "name": "description",
          "type": "text",
          "primaryKey": false,
          "notNull": false,
          "autoincrement": false
        },
        "fundraiserType": {
          "name": "fundraiserType",
          "type": "enum('direct_donation','micro_fundraiser')",
          "primaryKey": false,
          "notNull": true,
          "autoincrement": false
        },
        "fundraiserTemplate": {
          "name": "fundraiserTemplate",
          "type": "enum('direct_donation','micro_fundraiser','raffle','squares','challenge','team_vs_team','calendar','donation_matching')",
          "primaryKey": false,
          "notNull": true,
          "autoincrement": false,
          "default": "'direct_donation'"
        },
        "status": {
          "name": "status",
          "type": "enum('draft','active','paused','completed','cancelled')",
          "primaryKey": false,
          "notNull": true,
          "autoincrement": false,
          "default": "'draft'"
        },
        "startDate": {
          "name": "startDate",
          "type": "timestamp",
          "primaryKey": false,
          "notNull": false,
          "autoincrement": false
        },
        "endDate": {
          "name": "endDate",
          "type": "timestamp",
          "primaryKey": false,
          "notNull": false,
          "autoincrement": false
        },
        "goalAmount": {
          "name": "goalAmount",
          "type": "int",
          "primaryKey": false,
          "notNull": false,
          "autoincrement": false
        },
        "config": {
          "name": "config",
          "type": "text",
          "primaryKey": false,
          "notNull": false,
          "autoincrement": false
        },
        "publishedAt": {
          "name": "publishedAt",
          "type": "timestamp",
          "primaryKey": false,
          "notNull": false,
          "autoincrement": false
        },
        "completedAt": {
          "name": "completedAt",
          "type": "timestamp",
          "primaryKey": false,
          "notNull": false,
          "autoincrement": false
        },
        "totalAmountPledged": {
          "name": "totalAmountPledged",
          "type": "int",
          "primaryKey": false,
          "notNull": true,
          "autoincrement": false,
          "default": 0
        },
        "totalAmountCharged": {
          "name": "totalAmountCharged",
          "type": "int",
          "primaryKey": false,
          "notNull": true,
          "autoincrement": false,
          "default": 0
        },
        "createdAt": {
          "name": "createdAt",
          "type": "timestamp",
          "primaryKey": false,
          "notNull": true,
          "autoincrement": false,
          "default": "(now())"
        },
        "updatedAt": {
          "name": "updatedAt",
          "type": "timestamp",
          "primaryKey": false,
          "notNull": true,
          "autoincrement": false,
          "onUpdate": true,
          "default": "(now())"
        }
      },
      "indexes": {},
      "foreignKeys": {},
      "compositePrimaryKeys": {
        "fundraisers_id": {
          "name": "fundraisers_id",
          "columns": [
            "id"
          ]
        }
      },
      "uniqueConstraints": {},
      "checkConstraint": {}
    },
    "leagues": {
      "name": "leagues",
      "columns": {
        "id": {
          "name": "id",
          "type": "int",
          "primaryKey": false,
          "notNull": true,
          "autoincrement": true
        },
        "name": {
          "name": "name",
          "type": "varchar(255)",
          "primaryKey": false,
          "notNull": true,
          "autoincrement": false
        },
        "description": {
          "name": "description",
          "type": "text",
          "primaryKey": false,
          "notNull": false,
          "autoincrement": false
        },
        "logoUrl": {
          "name": "logoUrl",
          "type": "text",
          "primaryKey": false,
          "notNull": false,
          "autoincrement": false
        },
        "defaultFeePercentage": {
          "name": "defaultFeePercentage",
          "type": "int",
          "primaryKey": false,
          "notNull": true,
          "autoincrement": false,
          "default": 5
        },
        "allowedFundraiserTypes": {
          "name": "allowedFundraiserTypes",
          "type": "text",
          "primaryKey": false,
          "notNull": true,
          "autoincrement": false
        },
        "createdAt": {
          "name": "createdAt",
          "type": "timestamp",
          "primaryKey": false,
          "notNull": true,
          "autoincrement": false,
          "default": "(now())"
        },
        "updatedAt": {
          "name": "updatedAt",
          "type": "timestamp",
          "primaryKey": false,
          "notNull": true,
          "autoincrement": false,
          "onUpdate": true,
          "default": "(now())"
        }
      },
      "indexes": {},
      "foreignKeys": {},
      "compositePrimaryKeys": {
        "leagues_id": {
          "name": "leagues_id",
          "columns": [
            "id"
          ]
        }
      },
      "uniqueConstraints": {},
      "checkConstraint": {}
    },
    "notifications": {
      "name": "notifications",
      "columns": {
        "id": {
          "name": "id",
          "type": "int",
          "primaryKey": false,
          "notNull": true,
          "autoincrement": true
        },
        "recipientEmail": {
          "name": "recipientEmail",
          "type": "varchar(320)",
          "primaryKey": false,
          "notNull": true,
          "autoincrement": false
        },
        "subject": {
          "name": "subject",
          "type": "varchar(500)",
          "primaryKey": false,
          "notNull": true,
          "autoincrement": false
        },
        "templateName": {
          "name": "templateName",
          "type": "varchar(100)",
          "primaryKey": false,
          "notNull": true,
          "autoincrement": false
        },
        "templateData": {
          "name": "templateData",
          "type": "text",
          "primaryKey": false,
          "notNull": false,
          "autoincrement": false
        },
        "status": {
          "name": "status",
          "type": "enum('pending','sent','failed')",
          "primaryKey": false,
          "notNull": true,
          "autoincrement": false,
          "default": "'pending'"
        },
        "sentAt": {
          "name": "sentAt",
          "type": "timestamp",
          "primaryKey": false,
          "notNull": false,
          "autoincrement": false
        },
        "failureReason": {
          "name": "failureReason",
          "type": "text",
          "primaryKey": false,
          "notNull": false,
          "autoincrement": false
        },
        "createdAt": {
          "name": "createdAt",
          "type": "timestamp",
          "primaryKey": false,
          "notNull": true,
          "autoincrement": false,
          "default": "(now())"
        },
        "updatedAt": {
          "name": "updatedAt",
          "type": "timestamp",
          "primaryKey": false,
          "notNull": true,
          "autoincrement": false,
          "onUpdate": true,
          "default": "(now())"
        }
      },
      "indexes": {},
      "foreignKeys": {},
      "compositePrimaryKeys": {
        "notifications_id": {
          "name": "notifications_id",
          "columns": [
            "id"
          ]
        }
      },
      "uniqueConstraints": {},
      "checkConstraint": {}
    },
    "pledges": {
      "name": "pledges",
      "columns": {
        "id": {
          "name": "id",
          "type": "int",
          "primaryKey": false,
          "notNull": true,
          "autoincrement": true
        },
        "fundraiserId": {
          "name": "fundraiserId",
          "type": "int",
          "primaryKey": false,
          "notNull": true,
          "autoincrement": false
        },
        "donorName": {
          "name": "donorName",
          "type": "varchar(255)",
          "primaryKey": false,
          "notNull": true,
          "autoincrement": false
        },
        "donorEmail": {
          "name": "donorEmail",
          "type": "varchar(320)",
          "primaryKey": false,
          "notNull": true,
          "autoincrement": false
        },
        "donorPhone": {
          "name": "donorPhone",
          "type": "varchar(50)",
          "primaryKey": false,
          "notNull": false,
          "autoincrement": false
        },
        "pledgeType": {
          "name": "pledgeType",
          "type": "enum('direct_donation','micro_pledge')",
          "primaryKey": false,
          "notNull": true,
          "autoincrement": false
        },
        "baseAmount": {
          "name": "baseAmount",
          "type": "int",
          "primaryKey": false,
          "notNull": true,
          "autoincrement": false
        },
        "capAmount": {
          "name": "capAmount",
          "type": "int",
          "primaryKey": false,
          "notNull": false,
          "autoincrement": false
        },
        "multiplier": {
          "name": "multiplier",
          "type": "int",
          "primaryKey": false,
          "notNull": false,
          "autoincrement": false
        },
        "calculatedAmount": {
          "name": "calculatedAmount",
          "type": "int",
          "primaryKey": false,
          "notNull": false,
          "autoincrement": false
        },
        "finalAmount": {
          "name": "finalAmount",
          "type": "int",
          "primaryKey": false,
          "notNull": true,
          "autoincrement": false
        },
        "platformFee": {
          "name": "platformFee",
          "type": "int",
          "primaryKey": false,
          "notNull": true,
          "autoincrement": false
        },
        "donorTip": {
          "name": "donorTip",
          "type": "int",
          "primaryKey": false,
          "notNull": true,
          "autoincrement": false,
          "default": 0
        },
        "stripeCustomerId": {
          "name": "stripeCustomerId",
          "type": "varchar(255)",
          "primaryKey": false,
          "notNull": false,
          "autoincrement": false
        },
        "stripeSetupIntentId": {
          "name": "stripeSetupIntentId",
          "type": "varchar(255)",
          "primaryKey": false,
          "notNull": false,
          "autoincrement": false
        },
        "stripePaymentMethodId": {
          "name": "stripePaymentMethodId",
          "type": "varchar(255)",
          "primaryKey": false,
          "notNull": false,
          "autoincrement": false
        },
        "stripePaymentIntentId": {
          "name": "stripePaymentIntentId",
          "type": "varchar(255)",
          "primaryKey": false,
          "notNull": false,
          "autoincrement": false
        },
        "status": {
          "name": "status",
          "type": "enum('pending_authorization','authorized','charged','failed','refunded')",
          "primaryKey": false,
          "notNull": true,
          "autoincrement": false
        },
        "authorizedAt": {
          "name": "authorizedAt",
          "type": "timestamp",
          "primaryKey": false,
          "notNull": false,
          "autoincrement": false
        },
        "chargedAt": {
          "name": "chargedAt",
          "type": "timestamp",
          "primaryKey": false,
          "notNull": false,
          "autoincrement": false
        },
        "refundedAt": {
          "name": "refundedAt",
          "type": "timestamp",
          "primaryKey": false,
          "notNull": false,
          "autoincrement": false
        },
        "createdAt": {
          "name": "createdAt",
          "type": "timestamp",
          "primaryKey": false,
          "notNull": true,
          "autoincrement": false,
          "default": "(now())"
        },
        "updatedAt": {
          "name": "updatedAt",
          "type": "timestamp",
          "primaryKey": false,
          "notNull": true,
          "autoincrement": false,
          "onUpdate": true,
          "default": "(now())"
        }
      },
      "indexes": {},
      "foreignKeys": {},
      "compositePrimaryKeys": {
        "pledges_id": {
          "name": "pledges_id",
          "columns": [
            "id"
          ]
        }
      },
      "uniqueConstraints": {},
      "checkConstraint": {}
    },
    "raffleItems": {
      "name": "raffleItems",
      "columns": {
        "id": {
          "name": "id",
          "type": "int",
          "primaryKey": false,
          "notNull": true,
          "autoincrement": true
        },
        "fundraiserId": {
          "name": "fundraiserId",
          "type": "int",
          "primaryKey": false,
          "notNull": true,
          "autoincrement": false
        },
        "title": {
          "name": "title",
          "type": "varchar(255)",
          "primaryKey": false,
          "notNull": true,
          "autoincrement": false
        },
        "description": {
          "name": "description",
          "type": "text",
          "primaryKey": false,
          "notNull": false,
          "autoincrement": false
        },
        "imageUrl": {
          "name": "imageUrl",
          "type": "varchar(500)",
          "primaryKey": false,
          "notNull": false,
          "autoincrement": false
        },
        "sponsorName": {
          "name": "sponsorName",
          "type": "varchar(255)",
          "primaryKey": false,
          "notNull": false,
          "autoincrement": false
        },
        "sponsorLogoUrl": {
          "name": "sponsorLogoUrl",
          "type": "varchar(500)",
          "primaryKey": false,
          "notNull": false,
          "autoincrement": false
        },
        "totalEntries": {
          "name": "totalEntries",
          "type": "int",
          "primaryKey": false,
          "notNull": true,
          "autoincrement": false,
          "default": 0
        },
        "winnerPledgeId": {
          "name": "winnerPledgeId",
          "type": "int",
          "primaryKey": false,
          "notNull": false,
          "autoincrement": false
        },
        "drawnAt": {
          "name": "drawnAt",
          "type": "timestamp",
          "primaryKey": false,
          "notNull": false,
          "autoincrement": false
        },
        "createdAt": {
          "name": "createdAt",
          "type": "timestamp",
          "primaryKey": false,
          "notNull": true,
          "autoincrement": false,
          "default": "(now())"
        }
      },
      "indexes": {},
      "foreignKeys": {},
      "compositePrimaryKeys": {
        "raffleItems_id": {
          "name": "raffleItems_id",
          "columns": [
            "id"
          ]
        }
      },
      "uniqueConstraints": {},
      "checkConstraint": {}
    },
    "raffleTiers": {
      "name": "raffleTiers",
      "columns": {
        "id": {
          "name": "id",
          "type": "int",
          "primaryKey": false,
          "notNull": true,
          "autoincrement": true
        },
        "fundraiserId": {
          "name": "fundraiserId",
          "type": "int",
          "primaryKey": false,
          "notNull": true,
          "autoincrement": false
        },
        "price": {
          "name": "price",
          "type": "int",
          "primaryKey": false,
          "notNull": true,
          "autoincrement": false
        },
        "entries": {
          "name": "entries",
          "type": "int",
          "primaryKey": false,
          "notNull": true,
          "autoincrement": false
        },
        "label": {
          "name": "label",
          "type": "varchar(100)",
          "primaryKey": false,
          "notNull": false,
          "autoincrement": false
        },
        "createdAt": {
          "name": "createdAt",
          "type": "timestamp",
          "primaryKey": false,
          "notNull": true,
          "autoincrement": false,
          "default": "(now())"
        }
      },
      "indexes": {},
      "foreignKeys": {},
      "compositePrimaryKeys": {
        "raffleTiers_id": {
          "name": "raffleTiers_id",
          "columns": [
            "id"
          ]
        }
      },
      "uniqueConstraints": {},
      "checkConstraint": {}
    },
    "squaresGrids": {
      "name": "squaresGrids",
      "columns": {
        "id": {
          "name": "id",
          "type": "int",
          "primaryKey": false,
          "notNull": true,
          "autoincrement": true
        },
        "fundraiserId": {
          "name": "fundraiserId",
          "type": "int",
          "primaryKey": false,
          "notNull": true,
          "autoincrement": false
        },
        "gridSize": {
          "name": "gridSize",
          "type": "int",
          "primaryKey": false,
          "notNull": true,
          "autoincrement": false,
          "default": 100
        },
        "pricePerSquare": {
          "name": "pricePerSquare",
          "type": "int",
          "primaryKey": false,
          "notNull": true,
          "autoincrement": false
        },
        "homeTeam": {
          "name": "homeTeam",
          "type": "varchar(255)",
          "primaryKey": false,
          "notNull": false,
          "autoincrement": false
        },
        "awayTeam": {
          "name": "awayTeam",
          "type": "varchar(255)",
          "primaryKey": false,
          "notNull": false,
          "autoincrement": false
        },
        "eventDate": {
          "name": "eventDate",
          "type": "timestamp",
          "primaryKey": false,
          "notNull": false,
          "autoincrement": false
        },
        "homeNumbers": {
          "name": "homeNumbers",
          "type": "text",
          "primaryKey": false,
          "notNull": false,
          "autoincrement": false
        },
        "awayNumbers": {
          "name": "awayNumbers",
          "type": "text",
          "primaryKey": false,
          "notNull": false,
          "autoincrement": false
        },
        "numbersLocked": {
          "name": "numbersLocked",
          "type": "int",
          "primaryKey": false,
          "notNull": true,
          "autoincrement": false,
          "default": 0
        },
        "createdAt": {
          "name": "createdAt",
          "type": "timestamp",
          "primaryKey": false,
          "notNull": true,
          "autoincrement": false,
          "default": "(now())"
        }
      },
      "indexes": {},
      "foreignKeys": {},
      "compositePrimaryKeys": {
        "squaresGrids_id": {
          "name": "squaresGrids_id",
          "columns": [
            "id"
          ]
        }
      },
      "uniqueConstraints": {},
      "checkConstraint": {}
    },
    "squaresPayouts": {
      "name": "squaresPayouts",
      "columns": {
        "id": {
          "name": "id",
          "type": "int",
          "primaryKey": false,
          "notNull": true,
          "autoincrement": true
        },
        "gridId": {
          "name": "gridId",
          "type": "int",
          "primaryKey": false,
          "notNull": true,
          "autoincrement": false
        },
        "quarter": {
          "name": "quarter",
          "type": "int",
          "primaryKey": false,
          "notNull": false,
          "autoincrement": false
        },
        "homeScore": {
          "name": "homeScore",
          "type": "int",
          "primaryKey": false,
          "notNull": false,
          "autoincrement": false
        },
        "awayScore": {
          "name": "awayScore",
          "type": "int",
          "primaryKey": false,
          "notNull": false,
          "autoincrement": false
        },
        "winnerSquareId": {
          "name": "winnerSquareId",
          "type": "int",
          "primaryKey": false,
          "notNull": false,
          "autoincrement": false
        },
        "payoutAmount": {
          "name": "payoutAmount",
          "type": "int",
          "primaryKey": false,
          "notNull": false,
          "autoincrement": false
        },
        "paidAt": {
          "name": "paidAt",
          "type": "timestamp",
          "primaryKey": false,
          "notNull": false,
          "autoincrement": false
        },
        "createdAt": {
          "name": "createdAt",
          "type": "timestamp",
          "primaryKey": false,
          "notNull": true,
          "autoincrement": false,
          "default": "(now())"
        }
      },
      "indexes": {},
      "foreignKeys": {},
      "compositePrimaryKeys": {
        "squaresPayouts_id": {
          "name": "squaresPayouts_id",
          "columns": [
            "id"
          ]
        }
      },
      "uniqueConstraints": {},
      "checkConstraint": {}
    },
    "squaresPurchases": {
      "name": "squaresPurchases",
      "columns": {
        "id": {
          "name": "id",
          "type": "int",
          "primaryKey": false,
          "notNull": true,
          "autoincrement": true
        },
        "gridId": {
          "name": "gridId",
          "type": "int",
          "primaryKey": false,
          "notNull": true,
          "autoincrement": false
        },
        "pledgeId": {
          "name": "pledgeId",
          "type": "int",
          "primaryKey": false,
          "notNull": true,
          "autoincrement": false
        },
        "squarePosition": {
          "name": "squarePosition",
          "type": "int",
          "primaryKey": false,
          "notNull": true,
          "autoincrement": false
        },
        "donorName": {
          "name": "donorName",
          "type": "varchar(255)",
          "primaryKey": false,
          "notNull": false,
          "autoincrement": false
        },
        "purchasedAt": {
          "name": "purchasedAt",
          "type": "timestamp",
          "primaryKey": false,
          "notNull": true,
          "autoincrement": false,
          "default": "(now())"
        }
      },
      "indexes": {},
      "foreignKeys": {},
      "compositePrimaryKeys": {
        "squaresPurchases_id": {
          "name": "squaresPurchases_id",
          "columns": [
            "id"
          ]
        }
      },
      "uniqueConstraints": {},
      "checkConstraint": {}
    },
    "statsEntries": {
      "name": "statsEntries",
      "columns": {
        "id": {
          "name": "id",
          "type": "int",
          "primaryKey": false,
          "notNull": true,
          "autoincrement": true
        },
        "fundraiserId": {
          "name": "fundraiserId",
          "type": "int",
          "primaryKey": false,
          "notNull": true,
          "autoincrement": false
        },
        "metricName": {
          "name": "metricName",
          "type": "varchar(255)",
          "primaryKey": false,
          "notNull": true,
          "autoincrement": false
        },
        "metricValue": {
          "name": "metricValue",
          "type": "int",
          "primaryKey": false,
          "notNull": true,
          "autoincrement": false
        },
        "enteredBy": {
          "name": "enteredBy",
          "type": "int",
          "primaryKey": false,
          "notNull": true,
          "autoincrement": false
        },
        "notes": {
          "name": "notes",
          "type": "text",
          "primaryKey": false,
          "notNull": false,
          "autoincrement": false
        },
        "createdAt": {
          "name": "createdAt",
          "type": "timestamp",
          "primaryKey": false,
          "notNull": true,
          "autoincrement": false,
          "default": "(now())"
        },
        "updatedAt": {
          "name": "updatedAt",
          "type": "timestamp",
          "primaryKey": false,
          "notNull": true,
          "autoincrement": false,
          "onUpdate": true,
          "default": "(now())"
        }
      },
      "indexes": {},
      "foreignKeys": {},
      "compositePrimaryKeys": {
        "statsEntries_id": {
          "name": "statsEntries_id",
          "columns": [
            "id"
          ]
        }
      },
      "uniqueConstraints": {},
      "checkConstraint": {}
    },
    "teamVsTeamMatches": {
      "name": "teamVsTeamMatches",
      "columns": {
        "id": {
          "name": "id",
          "type": "int",
          "primaryKey": false,
          "notNull": true,
          "autoincrement": true
        },
        "fundraiser1Id": {
          "name": "fundraiser1Id",
          "type": "int",
          "primaryKey": false,
          "notNull": true,
          "autoincrement": false
        },
        "fundraiser2Id": {
          "name": "fundraiser2Id",
          "type": "int",
          "primaryKey": false,
          "notNull": true,
          "autoincrement": false
        },
        "loserChallenge": {
          "name": "loserChallenge",
          "type": "text",
          "primaryKey": false,
          "notNull": false,
          "autoincrement": false
        },
        "winnerId": {
          "name": "winnerId",
          "type": "int",
          "primaryKey": false,
          "notNull": false,
          "autoincrement": false
        },
        "completedAt": {
          "name": "completedAt",
          "type": "timestamp",
          "primaryKey": false,
          "notNull": false,
          "autoincrement": false
        },
        "createdAt": {
          "name": "createdAt",
          "type": "timestamp",
          "primaryKey": false,
          "notNull": true,
          "autoincrement": false,
          "default": "(now())"
        }
      },
      "indexes": {},
      "foreignKeys": {},
      "compositePrimaryKeys": {
        "teamVsTeamMatches_id": {
          "name": "teamVsTeamMatches_id",
          "columns": [
            "id"
          ]
        }
      },
      "uniqueConstraints": {},
      "checkConstraint": {}
    },
    "teams": {
      "name": "teams",
      "columns": {
        "id": {
          "name": "id",
          "type": "int",
          "primaryKey": false,
          "notNull": true,
          "autoincrement": true
        },
        "leagueId": {
          "name": "leagueId",
          "type": "int",
          "primaryKey": false,
          "notNull": true,
          "autoincrement": false
        },
        "name": {
          "name": "name",
          "type": "varchar(255)",
          "primaryKey": false,
          "notNull": true,
          "autoincrement": false
        },
        "description": {
          "name": "description",
          "type": "text",
          "primaryKey": false,
          "notNull": false,
          "autoincrement": false
        },
        "logoUrl": {
          "name": "logoUrl",
          "type": "text",
          "primaryKey": false,
          "notNull": false,
          "autoincrement": false
        },
        "stripeAccountId": {
          "name": "stripeAccountId",
          "type": "varchar(255)",
          "primaryKey": false,
          "notNull": false,
          "autoincrement": false
        },
        "stripeOnboardingCompleted": {
          "name": "stripeOnboardingCompleted",
          "type": "boolean",
          "primaryKey": false,
          "notNull": true,
          "autoincrement": false,
          "default": false
        },
        "stripeChargesEnabled": {
          "name": "stripeChargesEnabled",
          "type": "boolean",
          "primaryKey": false,
          "notNull": true,
          "autoincrement": false,
          "default": false
        },
        "stripePayoutsEnabled": {
          "name": "stripePayoutsEnabled",
          "type": "boolean",
          "primaryKey": false,
          "notNull": true,
          "autoincrement": false,
          "default": false
        },
        "feePercentage": {
          "name": "feePercentage",
          "type": "int",
          "primaryKey": false,
          "notNull": false,
          "autoincrement": false
        },
        "createdAt": {
          "name": "createdAt",
          "type": "timestamp",
          "primaryKey": false,
          "notNull": true,
          "autoincrement": false,
          "default": "(now())"
        },
        "updatedAt": {
          "name": "updatedAt",
          "type": "timestamp",
          "primaryKey": false,
          "notNull": true,
          "autoincrement": false,
          "onUpdate": true,
          "default": "(now())"
        }
      },
      "indexes": {},
      "foreignKeys": {},
      "compositePrimaryKeys": {
        "teams_id": {
          "name": "teams_id",
          "columns": [
            "id"
          ]
        }
      },
      "uniqueConstraints": {},
      "checkConstraint": {}
    },
    "userRoles": {
      "name": "userRoles",
      "columns": {
        "id": {
          "name": "id",
          "type": "int",
          "primaryKey": false,
          "notNull": true,
          "autoincrement": true
        },
        "userId": {
          "name": "userId",
          "type": "int",
          "primaryKey": false,
          "notNull": true,
          "autoincrement": false
        },
        "leagueId": {
          "name": "leagueId",
          "type": "int",
          "primaryKey": false,
          "notNull": false,
          "autoincrement": false
        },
        "teamId": {
          "name": "teamId",
          "type": "int",
          "primaryKey": false,
          "notNull": false,
          "autoincrement": false
        },
        "role": {
          "name": "role",
          "type": "enum('league_admin','team_manager')",
          "primaryKey": false,
          "notNull": true,
          "autoincrement": false
        },
        "grantedBy": {
          "name": "grantedBy",
          "type": "int",
          "primaryKey": false,
          "notNull": false,
          "autoincrement": false
        },
        "grantedAt": {
          "name": "grantedAt",
          "type": "timestamp",
          "primaryKey": false,
          "notNull": true,
          "autoincrement": false,
          "default": "(now())"
        },
        "revokedAt": {
          "name": "revokedAt",
          "type": "timestamp",
          "primaryKey": false,
          "notNull": false,
          "autoincrement": false
        }
      },
      "indexes": {},
      "foreignKeys": {},
      "compositePrimaryKeys": {
        "userRoles_id": {
          "name": "userRoles_id",
          "columns": [
            "id"
          ]
        }
      },
      "uniqueConstraints": {},
      "checkConstraint": {}
    },
    "users": {
      "name": "users",
      "columns": {
        "id": {
          "name": "id",
          "type": "int",
          "primaryKey": false,
          "notNull": true,
          "autoincrement": true
        },
        "openId": {
          "name": "openId",
          "type": "varchar(64)",
          "primaryKey": false,
          "notNull": false,
          "autoincrement": false
        },
        "name": {
          "name": "name",
          "type": "text",
          "primaryKey": false,
          "notNull": false,
          "autoincrement": false
        },
        "email": {
          "name": "email",
          "type": "varchar(320)",
          "primaryKey": false,
          "notNull": true,
          "autoincrement": false
        },
        "passwordHash": {
          "name": "passwordHash",
          "type": "varchar(255)",
          "primaryKey": false,
          "notNull": false,
          "autoincrement": false
        },
        "loginMethod": {
          "name": "loginMethod",
          "type": "varchar(64)",
          "primaryKey": false,
          "notNull": false,
          "autoincrement": false
        },
        "role": {
          "name": "role",
          "type": "enum('user','admin')",
          "primaryKey": false,
          "notNull": true,
          "autoincrement": false,
          "default": "'user'"
        },
        "createdAt": {
          "name": "createdAt",
          "type": "timestamp",
          "primaryKey": false,
          "notNull": true,
          "autoincrement": false,
          "default": "(now())"
        },
        "updatedAt": {
          "name": "updatedAt",
          "type": "timestamp",
          "primaryKey": false,
          "notNull": true,
          "autoincrement": false,
          "onUpdate": true,
          "default": "(now())"
        },
        "lastSignedIn": {
          "name": "lastSignedIn",
          "type": "timestamp",
          "primaryKey": false,
          "notNull": true,
          "autoincrement": false,
          "default": "(now())"
        }
      },
      "indexes": {},
      "foreignKeys": {},
      "compositePrimaryKeys": {
        "users_id": {
          "name": "users_id",
          "columns": [
            "id"
          ]
        }
      },
      "uniqueConstraints": {
        "users_openId_unique": {
          "name": "users_openId_unique",
          "columns": [
            "openId"
          ]
        },
        "users_email_unique": {
          "name": "users_email_unique",
          "columns": [
            "email"
          ]
        }
      },
      "checkConstraint": {}
    }
  },
  "views": {},
  "_meta": {
    "schemas": {},
    "tables": {},
    "columns": {}
  },
  "internal": {
    "tables": {},
    "indexes": {}
  }
}